{
  "id": "86314",
  "slug": "seated-neck-turns-head-rotations",
  "title": "Seated Neck Turns / Head Rotations",
  "description": "Seated Neck Turns is a at-home work out exercise that targets neck & upper traps",
  "equipment": [
    "NO EQUIPMENT"
  ],
  "primary_muscles": [
    "Neck Upper Traps"
  ],
  "secondary_muscles": [],
  "related_exercises": [
    "Seated Neck Turns / Head Rotations",
    "Seated Neck Roll",
    "Seated Bent Over Rear Delt Raises"
  ],
  "images": {
    "male": "https://workoutlabs.com/train/svg.php?id=86314",
    "female": "https://workoutlabs.com/train/svg.php?id=86315"
  }
}