{
  "id": "83453",
  "slug": "barbell-overhead-squats",
  "title": "Barbell Overhead Squats",
  "description": "Barbell Overhead Squats is a gym work out exercise that targets calves and hamstrings and quadriceps and also involves abs and shoulders",
  "equipment": [
    "Barbell / EZ-Bar"
  ],
  "primary_muscles": [
    "Calves",
    "Hamstrings",
    "Quadriceps"
  ],
  "secondary_muscles": [
    "Abs",
    "Shoulders"
  ],
  "related_exercises": [
    "Sumo / Plié Dumbbell Squats",
    "Bodyweight Calf Raises",
    "Bosu Ball Single / One Leg Pistol Squats"
  ],
  "images": {
    "male": "https://workoutlabs.com/train/svg.php?id=83453",
    "female": "https://workoutlabs.com/train/svg.php?id=85369"
  }
}