{
  "id": "78534",
  "slug": "foam-roller-anterior-tibialis-shin-stretch",
  "title": "Foam Roller Anterior Tibialis / Shin Stretch",
  "description": "Place a foam roller horizontally on the ground and get into a push-up position above the foam roller Lift one leg off the ground and place your shin onto the upper surface of the foam roller Apply a little pressure and gently roll up and down, using your hands and grounded foot to remain steady Roll your shin from side to side to reach all areas of your anterior tibialis",
  "equipment": [
    "Foam roller"
  ],
  "primary_muscles": [],
  "secondary_muscles": [
    "Calves"
  ],
  "related_exercises": [],
  "images": {
    "male": "https://workoutlabs.com/train/svg.php?id=84161",
    "female": "https://workoutlabs.com/train/svg.php?id=86158"
  }
}